reutils/__init__.py
reutils/cache.py
reutils/config.py
reutils/iterutils.py
reutils/json.py
reutils/logging.py
reutils/logging_v2.py
reutils/parallel.py
reutils-0.1.0.dist-info/LICENSE
reutils-0.1.0.dist-info/METADATA
reutils-0.1.0.dist-info/WHEEL
reutils-0.1.0.dist-info/top_level.txt
reutils-0.1.0.dist-info/RECORD
